[{"timestamp":"2023-10-01T06:17:58.296Z","count":207,"uniques":17},{"timestamp":"2023-11-01T18:17:13.239Z","count":202,"uniques":20},{"timestamp":"2023-12-01T01:20:25.966Z","count":102,"uniques":10},{"timestamp":"2024-01-01T06:30:07.939Z","count":9,"uniques":3},{"timestamp":"2024-02-01T01:15:43.428Z","count":19,"uniques":3},{"timestamp":"2024-03-01T06:33:03.889Z","count":82,"uniques":9},{"timestamp":"2024-04-01T18:21:27.264Z","count":142,"uniques":20},{"timestamp":"2024-05-01T12:17:54.949Z","count":11,"uniques":2},{"timestamp":"2024-06-01T06:18:42.085Z","count":21,"uniques":4},{"timestamp":"2024-07-01T18:17:58.845Z","count":30,"uniques":5},{"timestamp":"2024-08-01T18:17:54.142Z","count":60,"uniques":6},{"timestamp":"2024-09-01T00:34:21.699Z","count":0,"uniques":0},{"timestamp":"2024-10-01T06:19:02.247Z","count":36,"uniques":4}]
