[{"timestamp":"2025-02-05T00:38:36.856Z","count":0,"uniques":0},{"timestamp":"2025-02-06T00:38:50.812Z","count":0,"uniques":0},{"timestamp":"2025-02-07T00:39:05.252Z","count":0,"uniques":0},{"timestamp":"2025-02-08T06:23:19.707Z","count":0,"uniques":0},{"timestamp":"2025-02-09T00:40:44.627Z","count":0,"uniques":0},{"timestamp":"2025-02-10T00:41:27.050Z","count":0,"uniques":0},{"timestamp":"2025-02-11T00:41:25.827Z","count":0,"uniques":0},{"timestamp":"2025-02-12T00:40:37.132Z","count":0,"uniques":0},{"timestamp":"2025-02-13T00:39:16.138Z","count":0,"uniques":0},{"timestamp":"2025-02-14T00:39:22.602Z","count":0,"uniques":0},{"timestamp":"2025-02-15T00:38:24.714Z","count":0,"uniques":0},{"timestamp":"2025-02-16T00:43:05.131Z","count":0,"uniques":0},{"timestamp":"2025-02-17T00:42:21.898Z","count":0,"uniques":0},{"timestamp":"2025-02-18T00:40:34.355Z","count":0,"uniques":0},{"timestamp":"2025-02-19T00:39:04.661Z","count":0,"uniques":0},{"timestamp":"2025-02-20T00:39:01.143Z","count":0,"uniques":0},{"timestamp":"2025-02-21T00:39:56.662Z","count":0,"uniques":0},{"timestamp":"2025-02-22T00:38:18.601Z","count":0,"uniques":0},{"timestamp":"2025-02-23T00:42:46.512Z","count":0,"uniques":0},{"timestamp":"2025-02-24T00:40:54.593Z","count":0,"uniques":0},{"timestamp":"2025-02-25T00:39:49.588Z","count":0,"uniques":0},{"timestamp":"2025-02-26T00:41:00.017Z","count":0,"uniques":0},{"timestamp":"2025-02-27T00:41:48.182Z","count":0,"uniques":0},{"timestamp":"2025-02-28T00:40:05.024Z","count":0,"uniques":0},{"timestamp":"2025-03-01T00:42:18.707Z","count":0,"uniques":0},{"timestamp":"2025-03-02T00:41:47.348Z","count":0,"uniques":0},{"timestamp":"2025-03-03T00:41:28.814Z","count":0,"uniques":0},{"timestamp":"2025-03-04T00:41:40.948Z","count":0,"uniques":0},{"timestamp":"2025-03-05T06:22:48.334Z","count":0,"uniques":0},{"timestamp":"2025-03-06T00:42:04.580Z","count":0,"uniques":0},{"timestamp":"2025-03-07T00:40:07.106Z","count":0,"uniques":0},{"timestamp":"2025-03-08T00:36:48.039Z","count":0,"uniques":0},{"timestamp":"2025-03-09T00:39:53.556Z","count":0,"uniques":0},{"timestamp":"2025-03-10T00:38:15.052Z","count":0,"uniques":0},{"timestamp":"2025-03-11T00:40:33.017Z","count":0,"uniques":0},{"timestamp":"2025-03-12T00:40:06.337Z","count":0,"uniques":0},{"timestamp":"2025-03-13T00:40:23.912Z","count":0,"uniques":0},{"timestamp":"2025-03-14T00:39:53.308Z","count":0,"uniques":0},{"timestamp":"2025-03-15T00:39:29.443Z","count":0,"uniques":0},{"timestamp":"2025-03-16T00:43:08.442Z","count":0,"uniques":0},{"timestamp":"2025-03-17T00:41:35.708Z","count":0,"uniques":0},{"timestamp":"2025-03-18T00:40:38.655Z","count":0,"uniques":0},{"timestamp":"2025-03-19T00:40:44.517Z","count":0,"uniques":0},{"timestamp":"2025-03-20T00:42:29.261Z","count":0,"uniques":0},{"timestamp":"2025-03-21T00:40:36.279Z","count":0,"uniques":0},{"timestamp":"2025-03-22T00:39:47.859Z","count":0,"uniques":0},{"timestamp":"2025-03-23T00:43:03.677Z","count":0,"uniques":0},{"timestamp":"2025-03-24T00:44:22.757Z","count":0,"uniques":0},{"timestamp":"2025-03-25T00:40:52.662Z","count":0,"uniques":0},{"timestamp":"2025-03-26T00:42:05.676Z","count":0,"uniques":0},{"timestamp":"2025-03-27T00:41:19.141Z","count":0,"uniques":0},{"timestamp":"2025-03-28T00:40:26.645Z","count":0,"uniques":0},{"timestamp":"2025-03-29T00:40:36.727Z","count":0,"uniques":0},{"timestamp":"2025-03-30T00:43:50.382Z","count":0,"uniques":0},{"timestamp":"2025-03-31T00:42:51.372Z","count":0,"uniques":0},{"timestamp":"2025-04-01T00:45:11.665Z","count":0,"uniques":0},{"timestamp":"2025-04-02T00:42:05.660Z","count":0,"uniques":0},{"timestamp":"2025-04-03T00:40:19.736Z","count":0,"uniques":0},{"timestamp":"2025-04-04T00:42:39.229Z","count":0,"uniques":0},{"timestamp":"2025-04-05T00:40:35.403Z","count":0,"uniques":0},{"timestamp":"2025-04-06T00:44:57.942Z","count":0,"uniques":0},{"timestamp":"2025-04-07T00:44:07.597Z","count":0,"uniques":0},{"timestamp":"2025-04-08T00:42:33.029Z","count":0,"uniques":0},{"timestamp":"2025-04-09T00:41:19.029Z","count":0,"uniques":0},{"timestamp":"2025-04-10T00:42:24.384Z","count":0,"uniques":0},{"timestamp":"2025-04-11T00:41:24.110Z","count":0,"uniques":0},{"timestamp":"2025-04-12T00:40:54.229Z","count":0,"uniques":0},{"timestamp":"2025-04-13T00:00:00.000Z","count":4,"uniques":1},{"timestamp":"2025-04-14T00:43:28.901Z","count":0,"uniques":0},{"timestamp":"2025-04-15T00:42:25.500Z","count":0,"uniques":0},{"timestamp":"2025-04-16T14:25:14.845Z","count":0,"uniques":0},{"timestamp":"2025-04-17T14:25:14.845Z","count":0,"uniques":0},{"timestamp":"2025-04-18T14:25:14.845Z","count":0,"uniques":0},{"timestamp":"2025-04-19T14:25:14.845Z","count":0,"uniques":0},{"timestamp":"2025-04-20T14:25:14.845Z","count":0,"uniques":0},{"timestamp":"2025-04-21T14:25:14.845Z","count":0,"uniques":0},{"timestamp":"2025-04-22T14:25:14.845Z","count":0,"uniques":0},{"timestamp":"2025-04-23T14:25:14.845Z","count":0,"uniques":0},{"timestamp":"2025-04-24T14:25:14.845Z","count":0,"uniques":0},{"timestamp":"2025-04-25T14:25:14.845Z","count":0,"uniques":0},{"timestamp":"2025-04-26T14:25:14.845Z","count":0,"uniques":0},{"timestamp":"2025-04-27T14:25:14.845Z","count":0,"uniques":0},{"timestamp":"2025-04-28T14:25:14.845Z","count":0,"uniques":0},{"timestamp":"2025-04-29T14:25:14.845Z","count":0,"uniques":0},{"timestamp":"2025-04-30T14:25:14.845Z","count":0,"uniques":0},{"timestamp":"2025-05-01T14:25:14.845Z","count":0,"uniques":0},{"timestamp":"2025-05-02T14:25:14.845Z","count":0,"uniques":0},{"timestamp":"2025-05-03T14:25:14.845Z","count":0,"uniques":0},{"timestamp":"2025-05-04T14:25:14.845Z","count":0,"uniques":0},{"timestamp":"2025-05-05T00:00:00.000Z","count":2,"uniques":1},{"timestamp":"2025-05-06T14:25:14.845Z","count":0,"uniques":0},{"timestamp":"2025-05-07T14:25:14.845Z","count":0,"uniques":0},{"timestamp":"2025-05-08T14:25:14.845Z","count":0,"uniques":0},{"timestamp":"2025-05-09T14:25:14.845Z","count":0,"uniques":0},{"timestamp":"2025-05-10T14:25:14.845Z","count":0,"uniques":0},{"timestamp":"2025-05-11T00:00:00.000Z","count":1,"uniques":1},{"timestamp":"2025-05-12T14:25:14.845Z","count":0,"uniques":0},{"timestamp":"2025-05-13T14:25:14.845Z","count":0,"uniques":0},{"timestamp":"2025-05-14T14:25:14.845Z","count":0,"uniques":0},{"timestamp":"2025-05-15T14:25:14.845Z","count":0,"uniques":0},{"timestamp":"2025-05-16T14:25:14.845Z","count":0,"uniques":0},{"timestamp":"2025-05-17T14:25:14.845Z","count":0,"uniques":0},{"timestamp":"2025-05-18T14:25:14.845Z","count":0,"uniques":0},{"timestamp":"2025-05-19T00:45:46.190Z","count":0,"uniques":0},{"timestamp":"2025-05-20T00:45:22.185Z","count":0,"uniques":0},{"timestamp":"2025-05-21T00:43:28.522Z","count":0,"uniques":0},{"timestamp":"2025-05-22T06:23:55.131Z","count":0,"uniques":0},{"timestamp":"2025-05-23T00:43:24.348Z","count":0,"uniques":0},{"timestamp":"2025-05-24T00:41:46.298Z","count":0,"uniques":0},{"timestamp":"2025-05-25T00:47:48.292Z","count":0,"uniques":0},{"timestamp":"2025-05-26T00:43:57.254Z","count":0,"uniques":0},{"timestamp":"2025-05-27T00:43:38.579Z","count":0,"uniques":0},{"timestamp":"2025-05-28T00:44:28.479Z","count":0,"uniques":0},{"timestamp":"2025-05-29T00:42:44.204Z","count":0,"uniques":0},{"timestamp":"2025-05-30T00:43:07.659Z","count":0,"uniques":0},{"timestamp":"2025-05-31T00:43:43.318Z","count":0,"uniques":0},{"timestamp":"2025-06-01T00:50:04.947Z","count":0,"uniques":0},{"timestamp":"2025-06-02T00:45:48.231Z","count":0,"uniques":0},{"timestamp":"2025-06-03T00:45:20.410Z","count":0,"uniques":0},{"timestamp":"2025-06-04T00:43:18.646Z","count":0,"uniques":0},{"timestamp":"2025-06-05T00:44:47.722Z","count":0,"uniques":0},{"timestamp":"2025-06-06T00:42:59.956Z","count":0,"uniques":0},{"timestamp":"2025-06-07T00:44:26.843Z","count":0,"uniques":0},{"timestamp":"2025-06-08T00:47:14.256Z","count":0,"uniques":0},{"timestamp":"2025-06-09T00:47:59.898Z","count":0,"uniques":0},{"timestamp":"2025-06-10T06:24:09.184Z","count":0,"uniques":0},{"timestamp":"2025-06-11T00:43:47.767Z","count":0,"uniques":0},{"timestamp":"2025-06-12T00:42:58.727Z","count":0,"uniques":0},{"timestamp":"2025-06-13T00:43:35.125Z","count":0,"uniques":0},{"timestamp":"2025-06-14T00:43:41.961Z","count":0,"uniques":0},{"timestamp":"2025-06-15T00:46:43.632Z","count":0,"uniques":0},{"timestamp":"2025-06-16T00:45:18.501Z","count":0,"uniques":0},{"timestamp":"2025-06-17T00:43:32.198Z","count":0,"uniques":0},{"timestamp":"2025-06-18T00:43:34.804Z","count":0,"uniques":0},{"timestamp":"2025-06-19T00:45:33.904Z","count":0,"uniques":0},{"timestamp":"2025-06-20T00:43:32.181Z","count":0,"uniques":0},{"timestamp":"2025-06-21T00:45:19.168Z","count":0,"uniques":0},{"timestamp":"2025-06-22T00:46:18.440Z","count":0,"uniques":0},{"timestamp":"2025-06-23T00:46:18.216Z","count":0,"uniques":0},{"timestamp":"2025-06-24T00:43:42.895Z","count":0,"uniques":0},{"timestamp":"2025-06-25T00:45:10.951Z","count":0,"uniques":0},{"timestamp":"2025-06-26T00:44:10.845Z","count":0,"uniques":0},{"timestamp":"2025-06-27T00:43:43.402Z","count":0,"uniques":0},{"timestamp":"2025-06-28T00:42:11.903Z","count":0,"uniques":0},{"timestamp":"2025-06-29T00:47:47.918Z","count":0,"uniques":0},{"timestamp":"2025-06-30T00:47:48.135Z","count":0,"uniques":0},{"timestamp":"2025-07-01T00:48:10.935Z","count":0,"uniques":0},{"timestamp":"2025-07-02T00:45:32.327Z","count":0,"uniques":0},{"timestamp":"2025-07-03T00:45:42.398Z","count":0,"uniques":0},{"timestamp":"2025-07-04T00:46:04.452Z","count":0,"uniques":0},{"timestamp":"2025-07-05T00:42:06.501Z","count":0,"uniques":0},{"timestamp":"2025-07-06T00:48:57.063Z","count":0,"uniques":0},{"timestamp":"2025-07-07T00:46:06.155Z","count":0,"uniques":0},{"timestamp":"2025-07-08T00:45:23.165Z","count":0,"uniques":0},{"timestamp":"2025-07-09T00:47:01.328Z","count":0,"uniques":0},{"timestamp":"2025-07-10T00:44:05.065Z","count":0,"uniques":0},{"timestamp":"2025-07-11T09:31:42.295Z","count":0,"uniques":0},{"timestamp":"2025-07-12T00:44:20.342Z","count":0,"uniques":0},{"timestamp":"2025-07-13T00:48:20.426Z","count":0,"uniques":0},{"timestamp":"2025-07-14T00:47:02.548Z","count":0,"uniques":0},{"timestamp":"2025-07-15T00:45:38.873Z","count":0,"uniques":0},{"timestamp":"2025-07-16T00:45:33.323Z","count":0,"uniques":0},{"timestamp":"2025-07-17T00:46:24.449Z","count":0,"uniques":0},{"timestamp":"2025-07-18T00:45:40.944Z","count":0,"uniques":0},{"timestamp":"2025-07-19T00:45:07.794Z","count":0,"uniques":0},{"timestamp":"2025-07-20T00:38:42.733Z","count":0,"uniques":0},{"timestamp":"2025-07-21T00:39:42.115Z","count":0,"uniques":0},{"timestamp":"2025-07-22T00:34:22.717Z","count":0,"uniques":0},{"timestamp":"2025-07-23T00:35:23.543Z","count":0,"uniques":0},{"timestamp":"2025-07-24T00:34:47.573Z","count":0,"uniques":0},{"timestamp":"2025-07-25T00:34:39.227Z","count":0,"uniques":0},{"timestamp":"2025-07-26T00:34:36.260Z","count":0,"uniques":0},{"timestamp":"2025-07-27T00:37:58.090Z","count":0,"uniques":0},{"timestamp":"2025-07-28T00:36:19.284Z","count":0,"uniques":0},{"timestamp":"2025-07-29T00:36:54.411Z","count":0,"uniques":0},{"timestamp":"2025-07-30T00:34:26.443Z","count":0,"uniques":0},{"timestamp":"2025-07-31T00:34:02.944Z","count":0,"uniques":0},{"timestamp":"2025-08-01T00:38:35.092Z","count":0,"uniques":0},{"timestamp":"2025-08-02T00:33:15.333Z","count":0,"uniques":0},{"timestamp":"2025-08-03T00:38:46.471Z","count":0,"uniques":0},{"timestamp":"2025-08-04T00:37:05.008Z","count":0,"uniques":0},{"timestamp":"2025-08-05T00:35:52.658Z","count":0,"uniques":0},{"timestamp":"2025-08-06T00:35:57.929Z","count":0,"uniques":0},{"timestamp":"2025-08-07T00:34:49.460Z","count":0,"uniques":0},{"timestamp":"2025-08-08T00:35:56.157Z","count":0,"uniques":0},{"timestamp":"2025-08-09T00:33:18.808Z","count":0,"uniques":0},{"timestamp":"2025-08-10T00:36:51.064Z","count":0,"uniques":0},{"timestamp":"2025-08-11T00:35:51.771Z","count":0,"uniques":0},{"timestamp":"2025-08-12T00:33:09.910Z","count":0,"uniques":0},{"timestamp":"2025-08-13T00:32:48.185Z","count":0,"uniques":0},{"timestamp":"2025-08-14T00:32:22.316Z","count":0,"uniques":0},{"timestamp":"2025-08-15T00:00:00.000Z","count":4,"uniques":1},{"timestamp":"2025-08-16T00:30:58.768Z","count":0,"uniques":0},{"timestamp":"2025-08-17T00:35:51.158Z","count":0,"uniques":0},{"timestamp":"2025-08-18T00:35:35.726Z","count":0,"uniques":0},{"timestamp":"2025-08-19T00:32:27.813Z","count":0,"uniques":0},{"timestamp":"2025-08-20T00:30:35.470Z","count":0,"uniques":0},{"timestamp":"2025-08-21T00:30:14.839Z","count":0,"uniques":0},{"timestamp":"2025-08-22T00:30:55.186Z","count":0,"uniques":0},{"timestamp":"2025-08-23T00:31:12.514Z","count":0,"uniques":0},{"timestamp":"2025-08-24T00:34:13.783Z","count":0,"uniques":0},{"timestamp":"2025-08-25T00:33:16.388Z","count":0,"uniques":0},{"timestamp":"2025-08-26T00:30:53.876Z","count":0,"uniques":0},{"timestamp":"2025-08-27T00:00:00.000Z","count":1,"uniques":1},{"timestamp":"2025-08-28T14:49:01.831Z","count":0,"uniques":0},{"timestamp":"2025-08-29T00:33:32.599Z","count":0,"uniques":0},{"timestamp":"2025-08-30T00:32:10.960Z","count":0,"uniques":0},{"timestamp":"2025-08-31T00:36:01.501Z","count":0,"uniques":0},{"timestamp":"2025-09-01T00:40:15.672Z","count":0,"uniques":0},{"timestamp":"2025-09-02T00:32:38.972Z","count":0,"uniques":0},{"timestamp":"2025-09-03T00:31:57.283Z","count":0,"uniques":0},{"timestamp":"2025-09-04T00:31:33.407Z","count":0,"uniques":0},{"timestamp":"2025-09-05T00:33:09.901Z","count":0,"uniques":0},{"timestamp":"2025-09-06T00:30:45.435Z","count":0,"uniques":0},{"timestamp":"2025-09-07T00:34:35.158Z","count":0,"uniques":0},{"timestamp":"2025-09-08T00:35:15.471Z","count":0,"uniques":0},{"timestamp":"2025-09-09T00:34:46.181Z","count":0,"uniques":0},{"timestamp":"2025-09-10T00:34:19.630Z","count":0,"uniques":0},{"timestamp":"2025-09-11T00:32:07.954Z","count":0,"uniques":0},{"timestamp":"2025-09-12T00:33:39.400Z","count":0,"uniques":0},{"timestamp":"2025-09-13T00:30:27.127Z","count":0,"uniques":0},{"timestamp":"2025-09-14T00:35:11.947Z","count":0,"uniques":0},{"timestamp":"2025-09-15T00:35:22.288Z","count":0,"uniques":0},{"timestamp":"2025-09-16T00:32:35.257Z","count":0,"uniques":0},{"timestamp":"2025-09-17T00:33:42.397Z","count":0,"uniques":0},{"timestamp":"2025-09-18T00:34:10.514Z","count":0,"uniques":0},{"timestamp":"2025-09-19T00:36:13.634Z","count":0,"uniques":0},{"timestamp":"2025-09-20T00:30:54.358Z","count":0,"uniques":0},{"timestamp":"2025-09-21T00:34:30.265Z","count":0,"uniques":0},{"timestamp":"2025-09-22T00:34:16.092Z","count":0,"uniques":0},{"timestamp":"2025-09-23T00:32:59.384Z","count":0,"uniques":0},{"timestamp":"2025-09-24T00:31:43.692Z","count":0,"uniques":0},{"timestamp":"2025-09-25T00:33:05.683Z","count":0,"uniques":0},{"timestamp":"2025-09-26T00:32:27.395Z","count":0,"uniques":0},{"timestamp":"2025-09-27T00:32:36.524Z","count":0,"uniques":0},{"timestamp":"2025-09-28T00:34:21.242Z","count":0,"uniques":0},{"timestamp":"2025-09-29T00:34:38.396Z","count":0,"uniques":0},{"timestamp":"2025-09-30T00:31:33.919Z","count":0,"uniques":0},{"timestamp":"2025-10-01T00:35:17.758Z","count":0,"uniques":0},{"timestamp":"2025-10-02T00:33:05.385Z","count":0,"uniques":0},{"timestamp":"2025-10-03T00:31:02.315Z","count":0,"uniques":0},{"timestamp":"2025-10-04T00:32:07.379Z","count":0,"uniques":0},{"timestamp":"2025-10-05T00:36:01.847Z","count":0,"uniques":0},{"timestamp":"2025-10-06T00:34:31.931Z","count":0,"uniques":0},{"timestamp":"2025-10-07T00:33:43.307Z","count":0,"uniques":0},{"timestamp":"2025-10-08T00:32:03.746Z","count":0,"uniques":0},{"timestamp":"2025-10-09T00:33:23.211Z","count":0,"uniques":0},{"timestamp":"2025-10-10T00:33:42.627Z","count":0,"uniques":0},{"timestamp":"2025-10-11T00:31:18.095Z","count":0,"uniques":0},{"timestamp":"2025-10-12T00:34:04.902Z","count":0,"uniques":0},{"timestamp":"2025-10-13T00:34:44.907Z","count":0,"uniques":0},{"timestamp":"2025-10-14T00:33:21.474Z","count":0,"uniques":0},{"timestamp":"2025-10-15T00:34:27.817Z","count":0,"uniques":0},{"timestamp":"2025-10-16T00:34:34.275Z","count":0,"uniques":0},{"timestamp":"2025-10-17T00:32:06.581Z","count":0,"uniques":0},{"timestamp":"2025-10-18T00:30:35.556Z","count":0,"uniques":0},{"timestamp":"2025-10-19T00:36:50.482Z","count":0,"uniques":0},{"timestamp":"2025-10-20T00:35:01.462Z","count":0,"uniques":0},{"timestamp":"2025-10-21T00:33:47.393Z","count":0,"uniques":0},{"timestamp":"2025-10-22T00:33:27.747Z","count":0,"uniques":0},{"timestamp":"2025-10-23T00:32:14.548Z","count":0,"uniques":0},{"timestamp":"2025-10-24T00:30:22.062Z","count":0,"uniques":0},{"timestamp":"2025-10-25T00:33:49.250Z","count":0,"uniques":0},{"timestamp":"2025-10-26T00:35:34.672Z","count":0,"uniques":0},{"timestamp":"2025-10-27T00:35:40.973Z","count":0,"uniques":0},{"timestamp":"2025-10-28T00:00:00.000Z","count":1,"uniques":1},{"timestamp":"2025-10-29T00:33:24.525Z","count":0,"uniques":0},{"timestamp":"2025-10-30T00:35:16.349Z","count":0,"uniques":0},{"timestamp":"2025-10-31T00:32:46.446Z","count":0,"uniques":0},{"timestamp":"2025-11-01T00:37:04.467Z","count":0,"uniques":0},{"timestamp":"2025-11-02T00:35:31.330Z","count":0,"uniques":0},{"timestamp":"2025-11-03T00:35:43.543Z","count":0,"uniques":0},{"timestamp":"2025-11-04T00:33:06.770Z","count":0,"uniques":0},{"timestamp":"2025-11-05T00:34:36.036Z","count":0,"uniques":0},{"timestamp":"2025-11-06T00:33:41.626Z","count":0,"uniques":0},{"timestamp":"2025-11-07T00:33:33.956Z","count":0,"uniques":0},{"timestamp":"2025-11-08T00:31:18.427Z","count":0,"uniques":0},{"timestamp":"2025-11-09T00:35:26.259Z","count":0,"uniques":0},{"timestamp":"2025-11-10T00:35:37.272Z","count":0,"uniques":0},{"timestamp":"2025-11-11T00:34:13.097Z","count":0,"uniques":0},{"timestamp":"2025-11-12T00:34:37.023Z","count":0,"uniques":0},{"timestamp":"2025-11-13T00:34:32.201Z","count":0,"uniques":0},{"timestamp":"2025-11-14T00:37:32.252Z","count":0,"uniques":0},{"timestamp":"2025-11-15T00:32:57.952Z","count":0,"uniques":0},{"timestamp":"2025-11-16T00:36:26.139Z","count":0,"uniques":0},{"timestamp":"2025-11-17T00:34:08.063Z","count":0,"uniques":0},{"timestamp":"2025-11-18T00:33:44.599Z","count":0,"uniques":0},{"timestamp":"2025-11-19T00:35:01.173Z","count":0,"uniques":0},{"timestamp":"2025-11-20T00:32:49.537Z","count":0,"uniques":0},{"timestamp":"2025-11-21T00:33:36.938Z","count":0,"uniques":0},{"timestamp":"2025-11-22T00:32:16.094Z","count":0,"uniques":0},{"timestamp":"2025-11-23T00:37:39.897Z","count":0,"uniques":0},{"timestamp":"2025-11-24T00:36:16.782Z","count":0,"uniques":0},{"timestamp":"2025-11-25T00:32:26.698Z","count":0,"uniques":0},{"timestamp":"2025-11-26T00:33:39.586Z","count":0,"uniques":0},{"timestamp":"2025-11-27T00:33:16.220Z","count":0,"uniques":0},{"timestamp":"2025-11-28T00:35:50.576Z","count":0,"uniques":0},{"timestamp":"2025-11-29T00:32:07.668Z","count":0,"uniques":0},{"timestamp":"2025-11-30T00:38:12.391Z","count":0,"uniques":0},{"timestamp":"2025-12-01T00:41:00.941Z","count":0,"uniques":0},{"timestamp":"2025-12-02T00:34:51.515Z","count":0,"uniques":0},{"timestamp":"2025-12-03T00:39:30.272Z","count":0,"uniques":0},{"timestamp":"2025-12-04T00:35:25.743Z","count":0,"uniques":0},{"timestamp":"2025-12-05T00:34:40.638Z","count":0,"uniques":0},{"timestamp":"2025-12-06T00:32:37.440Z","count":0,"uniques":0},{"timestamp":"2025-12-07T00:00:00.000Z","count":3,"uniques":1},{"timestamp":"2025-12-08T00:35:48.473Z","count":0,"uniques":0},{"timestamp":"2025-12-09T00:35:00.905Z","count":0,"uniques":0},{"timestamp":"2025-12-10T00:38:49.267Z","count":0,"uniques":0},{"timestamp":"2025-12-11T00:35:01.506Z","count":0,"uniques":0},{"timestamp":"2025-12-12T00:35:23.474Z","count":0,"uniques":0},{"timestamp":"2025-12-13T00:34:36.202Z","count":0,"uniques":0},{"timestamp":"2025-12-14T00:37:54.646Z","count":0,"uniques":0},{"timestamp":"2025-12-15T00:37:20.054Z","count":0,"uniques":0},{"timestamp":"2025-12-16T00:35:04.904Z","count":0,"uniques":0},{"timestamp":"2025-12-17T00:34:54.591Z","count":0,"uniques":0},{"timestamp":"2025-12-18T00:32:19.185Z","count":0,"uniques":0},{"timestamp":"2025-12-19T00:35:20.409Z","count":0,"uniques":0},{"timestamp":"2025-12-20T00:00:00.000Z","count":1,"uniques":1},{"timestamp":"2025-12-21T00:40:39.111Z","count":0,"uniques":0},{"timestamp":"2025-12-22T00:36:55.227Z","count":0,"uniques":0},{"timestamp":"2025-12-23T00:35:09.824Z","count":0,"uniques":0},{"timestamp":"2025-12-24T00:35:45.636Z","count":0,"uniques":0},{"timestamp":"2025-12-25T00:34:38.132Z","count":0,"uniques":0},{"timestamp":"2025-12-26T00:35:01.124Z","count":0,"uniques":0},{"timestamp":"2025-12-27T00:34:38.692Z","count":0,"uniques":0},{"timestamp":"2025-12-28T00:39:20.706Z","count":0,"uniques":0},{"timestamp":"2025-12-29T00:38:24.537Z","count":0,"uniques":0},{"timestamp":"2025-12-30T00:35:30.595Z","count":0,"uniques":0},{"timestamp":"2025-12-31T00:36:42.369Z","count":0,"uniques":0},{"timestamp":"2026-01-01T00:40:10.086Z","count":0,"uniques":0},{"timestamp":"2026-01-02T00:35:24.686Z","count":0,"uniques":0},{"timestamp":"2026-01-03T00:34:11.099Z","count":0,"uniques":0},{"timestamp":"2026-01-04T00:40:38.047Z","count":0,"uniques":0},{"timestamp":"2026-01-05T00:38:38.256Z","count":0,"uniques":0},{"timestamp":"2026-01-06T00:36:25.887Z","count":0,"uniques":0},{"timestamp":"2026-01-07T00:35:10.759Z","count":0,"uniques":0},{"timestamp":"2026-01-08T00:36:42.901Z","count":0,"uniques":0},{"timestamp":"2026-01-09T00:35:46.019Z","count":0,"uniques":0},{"timestamp":"2026-01-10T00:36:18.250Z","count":0,"uniques":0},{"timestamp":"2026-01-11T00:39:46.533Z","count":0,"uniques":0},{"timestamp":"2026-01-12T00:37:55.131Z","count":0,"uniques":0},{"timestamp":"2026-01-13T00:33:07.999Z","count":0,"uniques":0},{"timestamp":"2026-01-14T00:37:02.812Z","count":0,"uniques":0},{"timestamp":"2026-01-15T00:00:00.000Z","count":5,"uniques":1},{"timestamp":"2026-01-16T00:37:31.216Z","count":0,"uniques":0},{"timestamp":"2026-01-17T00:34:08.809Z","count":0,"uniques":0},{"timestamp":"2026-01-18T00:38:39.438Z","count":0,"uniques":0},{"timestamp":"2026-01-19T00:38:02.185Z","count":0,"uniques":0},{"timestamp":"2026-01-20T00:35:52.307Z","count":0,"uniques":0},{"timestamp":"2026-01-21T00:37:51.316Z","count":0,"uniques":0},{"timestamp":"2026-01-22T00:37:56.240Z","count":0,"uniques":0},{"timestamp":"2026-01-23T00:37:05.336Z","count":0,"uniques":0},{"timestamp":"2026-01-24T00:35:18.012Z","count":0,"uniques":0},{"timestamp":"2026-01-25T00:40:13.515Z","count":0,"uniques":0},{"timestamp":"2026-01-26T00:38:34.889Z","count":0,"uniques":0},{"timestamp":"2026-01-27T00:38:50.031Z","count":0,"uniques":0},{"timestamp":"2026-01-28T00:37:13.191Z","count":0,"uniques":0},{"timestamp":"2026-01-29T00:41:00.341Z","count":0,"uniques":0},{"timestamp":"2026-01-30T00:40:42.364Z","count":0,"uniques":0},{"timestamp":"2026-01-31T00:39:19.299Z","count":0,"uniques":0},{"timestamp":"2026-02-01T00:47:57.899Z","count":0,"uniques":0},{"timestamp":"2026-02-02T00:43:42.003Z","count":0,"uniques":0},{"timestamp":"2026-02-03T00:43:08.508Z","count":0,"uniques":0},{"timestamp":"2026-02-04T00:39:41.793Z","count":0,"uniques":0},{"timestamp":"2026-02-05T00:43:15.443Z","count":0,"uniques":0}]
