[{"timestamp":"2025-02-01T00:38:49.831Z","count":0,"uniques":0},{"timestamp":"2025-03-01T00:40:30.146Z","count":0,"uniques":0},{"timestamp":"2025-04-01T06:22:18.458Z","count":86,"uniques":13},{"timestamp":"2025-05-01T14:23:57.390Z","count":1,"uniques":1},{"timestamp":"2025-06-01T00:44:23.515Z","count":0,"uniques":0},{"timestamp":"2025-07-01T00:44:05.418Z","count":0,"uniques":0},{"timestamp":"2025-08-01T00:32:57.586Z","count":0,"uniques":0},{"timestamp":"2025-09-01T00:32:21.048Z","count":0,"uniques":0},{"timestamp":"2025-10-01T06:15:11.590Z","count":2,"uniques":2},{"timestamp":"2025-11-01T06:15:11.057Z","count":6,"uniques":4},{"timestamp":"2025-12-01T00:34:31.264Z","count":0,"uniques":0},{"timestamp":"2026-01-01T00:35:07.604Z","count":0,"uniques":0},{"timestamp":"2026-02-01T00:43:21.996Z","count":0,"uniques":0}]
