[{"timestamp":"2024-10-01T06:22:59.509Z","count":28,"uniques":8},{"timestamp":"2024-11-01T06:19:57.863Z","count":68,"uniques":20},{"timestamp":"2024-12-01T18:19:34.700Z","count":74,"uniques":11},{"timestamp":"2025-01-01T00:36:19.304Z","count":16,"uniques":1},{"timestamp":"2025-02-01T12:23:08.642Z","count":3,"uniques":1},{"timestamp":"2025-03-01T18:19:26.609Z","count":32,"uniques":8},{"timestamp":"2025-04-01T06:20:40.814Z","count":52,"uniques":13},{"timestamp":"2025-05-01T06:19:12.718Z","count":46,"uniques":6},{"timestamp":"2025-06-01T00:43:03.909Z","count":5,"uniques":2},{"timestamp":"2025-07-01T00:33:12.177Z","count":13,"uniques":2},{"timestamp":"2025-08-01T14:48:12.166Z","count":9,"uniques":3},{"timestamp":"2025-09-01T06:12:25.176Z","count":5,"uniques":3},{"timestamp":"2025-10-01T00:32:49.022Z","count":15,"uniques":4}]
