[{"timestamp":"2025-02-10T00:25:40.060Z","count":0,"uniques":0},{"timestamp":"2025-02-11T00:24:46.621Z","count":0,"uniques":0},{"timestamp":"2025-02-12T00:24:36.945Z","count":0,"uniques":0},{"timestamp":"2025-02-13T00:24:36.685Z","count":0,"uniques":0},{"timestamp":"2025-02-14T00:24:34.614Z","count":0,"uniques":0},{"timestamp":"2025-02-15T00:24:12.247Z","count":0,"uniques":0},{"timestamp":"2025-02-16T00:27:10.190Z","count":0,"uniques":0},{"timestamp":"2025-02-17T00:26:28.438Z","count":0,"uniques":0},{"timestamp":"2025-02-18T00:24:35.813Z","count":0,"uniques":0},{"timestamp":"2025-02-19T00:24:46.747Z","count":0,"uniques":0},{"timestamp":"2025-02-20T00:24:49.769Z","count":0,"uniques":0},{"timestamp":"2025-02-21T00:24:58.075Z","count":0,"uniques":0},{"timestamp":"2025-02-22T00:24:03.123Z","count":0,"uniques":0},{"timestamp":"2025-02-23T00:27:06.964Z","count":0,"uniques":0},{"timestamp":"2025-02-24T00:26:09.029Z","count":0,"uniques":0},{"timestamp":"2025-02-25T00:25:25.279Z","count":0,"uniques":0},{"timestamp":"2025-02-26T00:25:14.003Z","count":0,"uniques":0},{"timestamp":"2025-02-27T00:25:22.532Z","count":0,"uniques":0},{"timestamp":"2025-02-28T00:25:21.892Z","count":0,"uniques":0},{"timestamp":"2025-03-01T00:27:52.286Z","count":0,"uniques":0},{"timestamp":"2025-03-02T00:27:30.461Z","count":0,"uniques":0},{"timestamp":"2025-03-03T00:26:54.563Z","count":0,"uniques":0},{"timestamp":"2025-03-04T00:25:43.694Z","count":0,"uniques":0},{"timestamp":"2025-03-05T06:08:41.081Z","count":0,"uniques":0},{"timestamp":"2025-03-06T00:25:47.800Z","count":0,"uniques":0},{"timestamp":"2025-03-07T00:25:44.431Z","count":0,"uniques":0},{"timestamp":"2025-03-08T00:20:47.885Z","count":0,"uniques":0},{"timestamp":"2025-03-09T00:23:27.831Z","count":0,"uniques":0},{"timestamp":"2025-03-10T00:22:25.057Z","count":0,"uniques":0},{"timestamp":"2025-03-11T00:25:55.645Z","count":0,"uniques":0},{"timestamp":"2025-03-12T00:25:53.140Z","count":0,"uniques":0},{"timestamp":"2025-03-13T00:26:10.363Z","count":0,"uniques":0},{"timestamp":"2025-03-14T00:25:32.008Z","count":0,"uniques":0},{"timestamp":"2025-03-15T00:25:31.319Z","count":0,"uniques":0},{"timestamp":"2025-03-16T00:28:20.250Z","count":0,"uniques":0},{"timestamp":"2025-03-17T00:27:15.401Z","count":0,"uniques":0},{"timestamp":"2025-03-18T00:25:52.026Z","count":0,"uniques":0},{"timestamp":"2025-03-19T00:26:04.849Z","count":0,"uniques":0},{"timestamp":"2025-03-20T00:25:50.444Z","count":0,"uniques":0},{"timestamp":"2025-03-21T00:26:05.818Z","count":0,"uniques":0},{"timestamp":"2025-03-22T00:25:36.514Z","count":0,"uniques":0},{"timestamp":"2025-03-23T00:28:26.947Z","count":0,"uniques":0},{"timestamp":"2025-03-24T00:27:41.259Z","count":0,"uniques":0},{"timestamp":"2025-03-25T00:26:28.986Z","count":0,"uniques":0},{"timestamp":"2025-03-26T00:26:16.317Z","count":0,"uniques":0},{"timestamp":"2025-03-27T00:26:15.155Z","count":0,"uniques":0},{"timestamp":"2025-03-28T00:26:03.597Z","count":0,"uniques":0},{"timestamp":"2025-03-29T00:26:14.001Z","count":0,"uniques":0},{"timestamp":"2025-03-30T00:29:12.854Z","count":0,"uniques":0},{"timestamp":"2025-03-31T00:28:28.245Z","count":0,"uniques":0},{"timestamp":"2025-04-01T00:30:25.683Z","count":0,"uniques":0},{"timestamp":"2025-04-02T00:27:01.150Z","count":0,"uniques":0},{"timestamp":"2025-04-03T00:26:03.944Z","count":0,"uniques":0},{"timestamp":"2025-04-04T00:26:38.645Z","count":0,"uniques":0},{"timestamp":"2025-04-05T00:26:00.222Z","count":0,"uniques":0},{"timestamp":"2025-04-06T00:28:52.384Z","count":0,"uniques":0},{"timestamp":"2025-04-07T00:27:56.091Z","count":0,"uniques":0},{"timestamp":"2025-04-08T00:26:30.603Z","count":0,"uniques":0},{"timestamp":"2025-04-09T00:26:31.998Z","count":0,"uniques":0},{"timestamp":"2025-04-10T00:26:39.824Z","count":0,"uniques":0},{"timestamp":"2025-04-11T00:27:01.765Z","count":0,"uniques":0},{"timestamp":"2025-04-12T00:26:11.341Z","count":0,"uniques":0},{"timestamp":"2025-04-13T00:52:24.596Z","count":0,"uniques":0},{"timestamp":"2025-04-14T00:28:44.010Z","count":0,"uniques":0},{"timestamp":"2025-04-15T00:27:30.338Z","count":0,"uniques":0},{"timestamp":"2025-04-16T14:10:54.196Z","count":0,"uniques":0},{"timestamp":"2025-04-17T14:10:54.196Z","count":0,"uniques":0},{"timestamp":"2025-04-18T14:10:54.196Z","count":0,"uniques":0},{"timestamp":"2025-04-19T14:10:54.196Z","count":0,"uniques":0},{"timestamp":"2025-04-20T14:10:54.196Z","count":0,"uniques":0},{"timestamp":"2025-04-21T14:10:54.196Z","count":0,"uniques":0},{"timestamp":"2025-04-22T14:10:54.196Z","count":0,"uniques":0},{"timestamp":"2025-04-23T14:10:54.196Z","count":0,"uniques":0},{"timestamp":"2025-04-24T14:10:54.196Z","count":0,"uniques":0},{"timestamp":"2025-04-25T14:10:54.196Z","count":0,"uniques":0},{"timestamp":"2025-04-26T14:10:54.196Z","count":0,"uniques":0},{"timestamp":"2025-04-27T14:10:54.196Z","count":0,"uniques":0},{"timestamp":"2025-04-28T14:10:54.196Z","count":0,"uniques":0},{"timestamp":"2025-04-29T14:10:54.196Z","count":0,"uniques":0},{"timestamp":"2025-04-30T14:10:54.196Z","count":0,"uniques":0},{"timestamp":"2025-05-01T14:10:54.196Z","count":0,"uniques":0},{"timestamp":"2025-05-02T14:10:54.196Z","count":0,"uniques":0},{"timestamp":"2025-05-03T14:10:54.196Z","count":0,"uniques":0},{"timestamp":"2025-05-04T14:10:54.196Z","count":0,"uniques":0},{"timestamp":"2025-05-05T14:10:54.196Z","count":0,"uniques":0},{"timestamp":"2025-05-06T14:10:54.196Z","count":0,"uniques":0},{"timestamp":"2025-05-07T14:10:54.196Z","count":0,"uniques":0},{"timestamp":"2025-05-08T14:10:54.196Z","count":0,"uniques":0},{"timestamp":"2025-05-09T14:10:54.196Z","count":0,"uniques":0},{"timestamp":"2025-05-10T14:10:54.196Z","count":0,"uniques":0},{"timestamp":"2025-05-11T14:10:54.196Z","count":0,"uniques":0},{"timestamp":"2025-05-12T14:10:54.196Z","count":0,"uniques":0},{"timestamp":"2025-05-13T14:10:54.196Z","count":0,"uniques":0},{"timestamp":"2025-05-14T14:10:54.196Z","count":0,"uniques":0},{"timestamp":"2025-05-15T14:10:54.196Z","count":0,"uniques":0},{"timestamp":"2025-05-16T14:10:54.196Z","count":0,"uniques":0},{"timestamp":"2025-05-17T14:10:54.196Z","count":0,"uniques":0},{"timestamp":"2025-05-18T14:10:54.196Z","count":0,"uniques":0},{"timestamp":"2025-05-19T00:30:13.901Z","count":0,"uniques":0},{"timestamp":"2025-05-20T00:29:20.980Z","count":0,"uniques":0},{"timestamp":"2025-05-21T00:29:11.212Z","count":0,"uniques":0},{"timestamp":"2025-05-22T06:09:47.026Z","count":0,"uniques":0},{"timestamp":"2025-05-23T00:28:40.579Z","count":0,"uniques":0},{"timestamp":"2025-05-24T00:27:29.339Z","count":0,"uniques":0},{"timestamp":"2025-05-25T00:31:38.324Z","count":0,"uniques":0},{"timestamp":"2025-05-26T00:29:33.830Z","count":0,"uniques":0},{"timestamp":"2025-05-27T00:28:07.400Z","count":0,"uniques":0},{"timestamp":"2025-05-28T00:28:38.171Z","count":0,"uniques":0},{"timestamp":"2025-05-29T00:28:23.549Z","count":0,"uniques":0},{"timestamp":"2025-05-30T00:28:33.991Z","count":0,"uniques":0},{"timestamp":"2025-05-31T00:27:45.911Z","count":0,"uniques":0},{"timestamp":"2025-06-01T00:35:35.610Z","count":0,"uniques":0},{"timestamp":"2025-06-02T00:30:16.257Z","count":0,"uniques":0},{"timestamp":"2025-06-03T00:29:24.571Z","count":0,"uniques":0},{"timestamp":"2025-06-04T00:29:06.963Z","count":0,"uniques":0},{"timestamp":"2025-06-05T00:28:42.079Z","count":0,"uniques":0},{"timestamp":"2025-06-06T00:28:30.810Z","count":0,"uniques":0},{"timestamp":"2025-06-07T00:28:32.702Z","count":0,"uniques":0},{"timestamp":"2025-06-08T00:32:00.928Z","count":0,"uniques":0},{"timestamp":"2025-06-09T00:31:06.850Z","count":0,"uniques":0},{"timestamp":"2025-06-10T06:09:34.647Z","count":0,"uniques":0},{"timestamp":"2025-06-11T00:28:54.165Z","count":0,"uniques":0},{"timestamp":"2025-06-12T00:28:39.981Z","count":0,"uniques":0},{"timestamp":"2025-06-13T00:29:07.088Z","count":0,"uniques":0},{"timestamp":"2025-06-14T00:28:10.710Z","count":0,"uniques":0},{"timestamp":"2025-06-15T00:32:23.463Z","count":0,"uniques":0},{"timestamp":"2025-06-16T00:30:32.615Z","count":0,"uniques":0},{"timestamp":"2025-06-17T00:28:51.244Z","count":0,"uniques":0},{"timestamp":"2025-06-18T00:28:49.506Z","count":0,"uniques":0},{"timestamp":"2025-06-19T00:29:20.231Z","count":0,"uniques":0},{"timestamp":"2025-06-20T00:28:38.845Z","count":0,"uniques":0},{"timestamp":"2025-06-21T00:28:52.346Z","count":0,"uniques":0},{"timestamp":"2025-06-22T00:32:07.007Z","count":0,"uniques":0},{"timestamp":"2025-06-23T00:31:26.947Z","count":0,"uniques":0},{"timestamp":"2025-06-24T00:29:10.143Z","count":0,"uniques":0},{"timestamp":"2025-06-25T00:29:24.983Z","count":0,"uniques":0},{"timestamp":"2025-06-26T00:29:01.192Z","count":0,"uniques":0},{"timestamp":"2025-06-27T00:29:21.216Z","count":0,"uniques":0},{"timestamp":"2025-06-28T00:28:02.875Z","count":0,"uniques":0},{"timestamp":"2025-06-29T00:33:00.851Z","count":0,"uniques":0},{"timestamp":"2025-06-30T00:31:36.096Z","count":0,"uniques":0},{"timestamp":"2025-07-01T00:33:41.911Z","count":0,"uniques":0},{"timestamp":"2025-07-02T00:29:22.659Z","count":0,"uniques":0},{"timestamp":"2025-07-03T00:29:33.570Z","count":0,"uniques":0},{"timestamp":"2025-07-04T00:29:13.629Z","count":0,"uniques":0},{"timestamp":"2025-07-05T00:27:50.735Z","count":0,"uniques":0},{"timestamp":"2025-07-06T00:32:40.886Z","count":0,"uniques":0},{"timestamp":"2025-07-07T00:31:37.471Z","count":0,"uniques":0},{"timestamp":"2025-07-08T00:29:21.581Z","count":0,"uniques":0},{"timestamp":"2025-07-09T00:30:23.282Z","count":0,"uniques":0},{"timestamp":"2025-07-10T00:29:35.514Z","count":0,"uniques":0},{"timestamp":"2025-07-11T09:16:22.505Z","count":0,"uniques":0},{"timestamp":"2025-07-12T00:29:53.453Z","count":0,"uniques":0},{"timestamp":"2025-07-13T00:33:36.722Z","count":0,"uniques":0},{"timestamp":"2025-07-14T00:32:34.754Z","count":0,"uniques":0},{"timestamp":"2025-07-15T00:31:01.597Z","count":0,"uniques":0},{"timestamp":"2025-07-16T00:30:34.865Z","count":0,"uniques":0},{"timestamp":"2025-07-17T00:31:19.291Z","count":0,"uniques":0},{"timestamp":"2025-07-18T00:30:35.275Z","count":0,"uniques":0},{"timestamp":"2025-07-19T00:30:05.964Z","count":0,"uniques":0},{"timestamp":"2025-07-20T00:35:25.793Z","count":0,"uniques":0},{"timestamp":"2025-07-21T00:35:37.144Z","count":0,"uniques":0},{"timestamp":"2025-07-22T00:30:57.286Z","count":0,"uniques":0},{"timestamp":"2025-07-23T00:32:00.536Z","count":0,"uniques":0},{"timestamp":"2025-07-24T00:31:07.653Z","count":0,"uniques":0},{"timestamp":"2025-07-25T00:31:23.831Z","count":0,"uniques":0},{"timestamp":"2025-07-26T00:30:51.122Z","count":0,"uniques":0},{"timestamp":"2025-07-27T00:34:49.879Z","count":0,"uniques":0},{"timestamp":"2025-07-28T00:33:11.393Z","count":0,"uniques":0},{"timestamp":"2025-07-29T00:33:29.177Z","count":0,"uniques":0},{"timestamp":"2025-07-30T00:31:14.165Z","count":0,"uniques":0},{"timestamp":"2025-07-31T00:30:46.017Z","count":0,"uniques":0},{"timestamp":"2025-08-01T00:35:20.021Z","count":0,"uniques":0},{"timestamp":"2025-08-02T00:30:00.985Z","count":0,"uniques":0},{"timestamp":"2025-08-03T00:35:31.765Z","count":0,"uniques":0},{"timestamp":"2025-08-04T00:33:56.206Z","count":0,"uniques":0},{"timestamp":"2025-08-05T00:32:39.564Z","count":0,"uniques":0},{"timestamp":"2025-08-06T00:32:45.371Z","count":0,"uniques":0},{"timestamp":"2025-08-07T00:31:38.195Z","count":0,"uniques":0},{"timestamp":"2025-08-08T00:32:33.310Z","count":0,"uniques":0},{"timestamp":"2025-08-09T00:29:54.680Z","count":0,"uniques":0},{"timestamp":"2025-08-10T00:33:38.822Z","count":0,"uniques":0},{"timestamp":"2025-08-11T00:32:29.533Z","count":0,"uniques":0},{"timestamp":"2025-08-12T00:29:41.062Z","count":0,"uniques":0},{"timestamp":"2025-08-13T00:29:30.647Z","count":0,"uniques":0},{"timestamp":"2025-08-14T00:29:04.237Z","count":0,"uniques":0},{"timestamp":"2025-08-15T00:30:11.110Z","count":0,"uniques":0},{"timestamp":"2025-08-16T00:00:00.000Z","count":1,"uniques":1},{"timestamp":"2025-08-17T00:32:41.031Z","count":0,"uniques":0},{"timestamp":"2025-08-18T00:32:18.080Z","count":0,"uniques":0},{"timestamp":"2025-08-19T00:29:05.256Z","count":0,"uniques":0},{"timestamp":"2025-08-20T00:27:15.641Z","count":0,"uniques":0},{"timestamp":"2025-08-21T00:26:51.453Z","count":0,"uniques":0},{"timestamp":"2025-08-22T00:27:32.520Z","count":0,"uniques":0},{"timestamp":"2025-08-23T00:27:50.235Z","count":0,"uniques":0},{"timestamp":"2025-08-24T00:31:02.163Z","count":0,"uniques":0},{"timestamp":"2025-08-25T00:29:50.355Z","count":0,"uniques":0},{"timestamp":"2025-08-26T00:27:33.780Z","count":0,"uniques":0},{"timestamp":"2025-08-27T00:27:25.707Z","count":0,"uniques":0},{"timestamp":"2025-08-28T14:45:44.385Z","count":0,"uniques":0},{"timestamp":"2025-08-29T00:30:19.127Z","count":0,"uniques":0},{"timestamp":"2025-08-30T00:28:43.909Z","count":0,"uniques":0},{"timestamp":"2025-08-31T00:32:52.609Z","count":0,"uniques":0},{"timestamp":"2025-09-01T00:36:47.274Z","count":0,"uniques":0},{"timestamp":"2025-09-02T00:29:18.936Z","count":0,"uniques":0},{"timestamp":"2025-09-03T00:28:26.808Z","count":0,"uniques":0},{"timestamp":"2025-09-04T00:28:12.436Z","count":0,"uniques":0},{"timestamp":"2025-09-05T00:29:08.016Z","count":0,"uniques":0},{"timestamp":"2025-09-06T00:27:36.003Z","count":0,"uniques":0},{"timestamp":"2025-09-07T00:31:23.426Z","count":0,"uniques":0},{"timestamp":"2025-09-08T00:31:06.226Z","count":0,"uniques":0},{"timestamp":"2025-09-09T00:30:30.206Z","count":0,"uniques":0},{"timestamp":"2025-09-10T00:30:30.434Z","count":0,"uniques":0},{"timestamp":"2025-09-11T00:28:46.147Z","count":0,"uniques":0},{"timestamp":"2025-09-12T00:29:31.518Z","count":0,"uniques":0},{"timestamp":"2025-09-13T00:27:13.529Z","count":0,"uniques":0},{"timestamp":"2025-09-14T00:32:02.167Z","count":0,"uniques":0},{"timestamp":"2025-09-15T00:31:17.903Z","count":0,"uniques":0},{"timestamp":"2025-09-16T00:29:23.951Z","count":0,"uniques":0},{"timestamp":"2025-09-17T00:30:20.310Z","count":0,"uniques":0},{"timestamp":"2025-09-18T00:30:45.869Z","count":0,"uniques":0},{"timestamp":"2025-09-19T00:32:30.440Z","count":0,"uniques":0},{"timestamp":"2025-09-20T00:26:47.843Z","count":0,"uniques":0},{"timestamp":"2025-09-21T00:30:45.007Z","count":0,"uniques":0},{"timestamp":"2025-09-22T00:30:53.903Z","count":0,"uniques":0},{"timestamp":"2025-09-23T00:29:14.247Z","count":0,"uniques":0},{"timestamp":"2025-09-24T00:28:00.748Z","count":0,"uniques":0},{"timestamp":"2025-09-25T00:29:46.304Z","count":0,"uniques":0},{"timestamp":"2025-09-26T00:29:03.472Z","count":0,"uniques":0},{"timestamp":"2025-09-27T00:28:52.960Z","count":0,"uniques":0},{"timestamp":"2025-09-28T00:31:04.839Z","count":0,"uniques":0},{"timestamp":"2025-09-29T00:31:18.390Z","count":0,"uniques":0},{"timestamp":"2025-09-30T00:28:20.535Z","count":0,"uniques":0},{"timestamp":"2025-10-01T00:31:59.523Z","count":0,"uniques":0},{"timestamp":"2025-10-02T00:29:16.940Z","count":0,"uniques":0},{"timestamp":"2025-10-03T00:27:13.953Z","count":0,"uniques":0},{"timestamp":"2025-10-04T00:28:09.208Z","count":0,"uniques":0},{"timestamp":"2025-10-05T00:32:25.367Z","count":0,"uniques":0},{"timestamp":"2025-10-06T00:31:04.264Z","count":0,"uniques":0},{"timestamp":"2025-10-07T00:30:01.580Z","count":0,"uniques":0},{"timestamp":"2025-10-08T00:28:21.046Z","count":0,"uniques":0},{"timestamp":"2025-10-09T00:29:57.352Z","count":0,"uniques":0},{"timestamp":"2025-10-10T00:30:11.966Z","count":0,"uniques":0},{"timestamp":"2025-10-11T00:27:54.827Z","count":0,"uniques":0},{"timestamp":"2025-10-12T00:30:54.874Z","count":0,"uniques":0},{"timestamp":"2025-10-13T00:31:00.423Z","count":0,"uniques":0},{"timestamp":"2025-10-14T00:29:51.533Z","count":0,"uniques":0},{"timestamp":"2025-10-15T00:30:40.086Z","count":0,"uniques":0},{"timestamp":"2025-10-16T00:31:08.169Z","count":0,"uniques":0},{"timestamp":"2025-10-17T00:28:49.819Z","count":0,"uniques":0},{"timestamp":"2025-10-18T00:26:50.352Z","count":0,"uniques":0},{"timestamp":"2025-10-19T00:33:27.951Z","count":0,"uniques":0},{"timestamp":"2025-10-20T00:31:34.929Z","count":0,"uniques":0},{"timestamp":"2025-10-21T00:30:34.751Z","count":0,"uniques":0},{"timestamp":"2025-10-22T00:30:07.120Z","count":0,"uniques":0},{"timestamp":"2025-10-23T00:28:59.790Z","count":0,"uniques":0},{"timestamp":"2025-10-24T00:26:55.727Z","count":0,"uniques":0},{"timestamp":"2025-10-25T00:30:32.842Z","count":0,"uniques":0},{"timestamp":"2025-10-26T00:31:29.666Z","count":0,"uniques":0},{"timestamp":"2025-10-27T00:32:25.500Z","count":0,"uniques":0},{"timestamp":"2025-10-28T00:30:18.886Z","count":0,"uniques":0},{"timestamp":"2025-10-29T00:30:00.079Z","count":0,"uniques":0},{"timestamp":"2025-10-30T00:31:28.650Z","count":0,"uniques":0},{"timestamp":"2025-10-31T00:29:15.622Z","count":0,"uniques":0},{"timestamp":"2025-11-01T00:33:51.084Z","count":0,"uniques":0},{"timestamp":"2025-11-02T00:31:47.919Z","count":0,"uniques":0},{"timestamp":"2025-11-03T00:31:42.166Z","count":0,"uniques":0},{"timestamp":"2025-11-04T00:29:20.421Z","count":0,"uniques":0},{"timestamp":"2025-11-05T00:30:28.278Z","count":0,"uniques":0},{"timestamp":"2025-11-06T00:29:52.411Z","count":0,"uniques":0},{"timestamp":"2025-11-07T00:29:51.894Z","count":0,"uniques":0},{"timestamp":"2025-11-08T00:28:04.985Z","count":0,"uniques":0},{"timestamp":"2025-11-09T00:32:20.925Z","count":0,"uniques":0},{"timestamp":"2025-11-10T00:31:45.935Z","count":0,"uniques":0},{"timestamp":"2025-11-11T00:30:53.788Z","count":0,"uniques":0},{"timestamp":"2025-11-12T00:30:20.005Z","count":0,"uniques":0},{"timestamp":"2025-11-13T00:30:22.986Z","count":0,"uniques":0},{"timestamp":"2025-11-14T00:33:40.609Z","count":0,"uniques":0},{"timestamp":"2025-11-15T00:29:14.770Z","count":0,"uniques":0},{"timestamp":"2025-11-16T00:32:32.385Z","count":0,"uniques":0},{"timestamp":"2025-11-17T00:30:53.501Z","count":0,"uniques":0},{"timestamp":"2025-11-18T00:30:08.171Z","count":0,"uniques":0},{"timestamp":"2025-11-19T00:30:52.216Z","count":0,"uniques":0},{"timestamp":"2025-11-20T00:29:27.372Z","count":0,"uniques":0},{"timestamp":"2025-11-21T00:29:48.683Z","count":0,"uniques":0},{"timestamp":"2025-11-22T00:28:44.979Z","count":0,"uniques":0},{"timestamp":"2025-11-23T00:34:13.466Z","count":0,"uniques":0},{"timestamp":"2025-11-24T00:33:00.354Z","count":0,"uniques":0},{"timestamp":"2025-11-25T00:29:06.685Z","count":0,"uniques":0},{"timestamp":"2025-11-26T00:30:18.489Z","count":0,"uniques":0},{"timestamp":"2025-11-27T00:30:03.902Z","count":0,"uniques":0},{"timestamp":"2025-11-28T00:32:10.310Z","count":0,"uniques":0},{"timestamp":"2025-11-29T00:28:43.512Z","count":0,"uniques":0},{"timestamp":"2025-11-30T00:34:09.460Z","count":0,"uniques":0},{"timestamp":"2025-12-01T00:37:16.444Z","count":0,"uniques":0},{"timestamp":"2025-12-02T00:31:03.393Z","count":0,"uniques":0},{"timestamp":"2025-12-03T00:35:50.929Z","count":0,"uniques":0},{"timestamp":"2025-12-04T00:31:15.608Z","count":0,"uniques":0},{"timestamp":"2025-12-05T00:31:20.852Z","count":0,"uniques":0},{"timestamp":"2025-12-06T00:29:25.771Z","count":0,"uniques":0},{"timestamp":"2025-12-07T00:34:04.835Z","count":0,"uniques":0},{"timestamp":"2025-12-08T00:32:00.842Z","count":0,"uniques":0},{"timestamp":"2025-12-09T00:31:14.728Z","count":0,"uniques":0},{"timestamp":"2025-12-10T00:35:24.436Z","count":0,"uniques":0},{"timestamp":"2025-12-11T00:31:48.543Z","count":0,"uniques":0},{"timestamp":"2025-12-12T00:31:38.111Z","count":0,"uniques":0},{"timestamp":"2025-12-13T00:30:33.091Z","count":0,"uniques":0},{"timestamp":"2025-12-14T00:34:37.550Z","count":0,"uniques":0},{"timestamp":"2025-12-15T00:33:43.990Z","count":0,"uniques":0},{"timestamp":"2025-12-16T00:31:47.735Z","count":0,"uniques":0},{"timestamp":"2025-12-17T00:31:12.486Z","count":0,"uniques":0},{"timestamp":"2025-12-18T00:28:32.652Z","count":0,"uniques":0},{"timestamp":"2025-12-19T00:31:39.506Z","count":0,"uniques":0},{"timestamp":"2025-12-20T00:30:22.461Z","count":0,"uniques":0},{"timestamp":"2025-12-21T00:37:03.943Z","count":0,"uniques":0},{"timestamp":"2025-12-22T00:33:40.463Z","count":0,"uniques":0},{"timestamp":"2025-12-23T00:31:29.252Z","count":0,"uniques":0},{"timestamp":"2025-12-24T00:32:09.961Z","count":0,"uniques":0},{"timestamp":"2025-12-25T00:00:00.000Z","count":1,"uniques":1},{"timestamp":"2025-12-26T00:31:42.669Z","count":0,"uniques":0},{"timestamp":"2025-12-27T00:31:00.905Z","count":0,"uniques":0},{"timestamp":"2025-12-28T00:35:59.210Z","count":0,"uniques":0},{"timestamp":"2025-12-29T00:34:58.341Z","count":0,"uniques":0},{"timestamp":"2025-12-30T00:31:52.569Z","count":0,"uniques":0},{"timestamp":"2025-12-31T00:33:05.086Z","count":0,"uniques":0},{"timestamp":"2026-01-01T00:36:30.447Z","count":0,"uniques":0},{"timestamp":"2026-01-02T00:00:00.000Z","count":1,"uniques":1},{"timestamp":"2026-01-03T00:00:00.000Z","count":2,"uniques":1},{"timestamp":"2026-01-04T00:37:00.535Z","count":0,"uniques":0},{"timestamp":"2026-01-05T00:35:16.758Z","count":0,"uniques":0},{"timestamp":"2026-01-06T00:32:41.379Z","count":0,"uniques":0},{"timestamp":"2026-01-07T00:31:57.757Z","count":0,"uniques":0},{"timestamp":"2026-01-08T00:32:38.055Z","count":0,"uniques":0},{"timestamp":"2026-01-09T00:32:19.544Z","count":0,"uniques":0},{"timestamp":"2026-01-10T00:32:04.754Z","count":0,"uniques":0},{"timestamp":"2026-01-11T00:36:08.767Z","count":0,"uniques":0},{"timestamp":"2026-01-12T00:34:16.788Z","count":0,"uniques":0},{"timestamp":"2026-01-13T00:29:10.339Z","count":0,"uniques":0},{"timestamp":"2026-01-14T00:33:35.584Z","count":0,"uniques":0},{"timestamp":"2026-01-15T00:30:26.477Z","count":0,"uniques":0},{"timestamp":"2026-01-16T00:33:25.405Z","count":0,"uniques":0},{"timestamp":"2026-01-17T00:30:50.670Z","count":0,"uniques":0},{"timestamp":"2026-01-18T00:00:00.000Z","count":1,"uniques":1},{"timestamp":"2026-01-19T00:34:43.938Z","count":0,"uniques":0},{"timestamp":"2026-01-20T00:32:10.320Z","count":0,"uniques":0},{"timestamp":"2026-01-21T00:33:46.879Z","count":0,"uniques":0},{"timestamp":"2026-01-22T00:34:27.777Z","count":0,"uniques":0},{"timestamp":"2026-01-23T00:33:27.545Z","count":0,"uniques":0},{"timestamp":"2026-01-24T00:31:58.117Z","count":0,"uniques":0},{"timestamp":"2026-01-25T00:36:34.214Z","count":0,"uniques":0},{"timestamp":"2026-01-26T00:35:16.719Z","count":0,"uniques":0},{"timestamp":"2026-01-27T00:34:58.811Z","count":0,"uniques":0},{"timestamp":"2026-01-28T00:33:34.643Z","count":0,"uniques":0},{"timestamp":"2026-01-29T00:37:21.491Z","count":0,"uniques":0},{"timestamp":"2026-01-30T00:37:26.665Z","count":0,"uniques":0},{"timestamp":"2026-01-31T00:36:01.111Z","count":0,"uniques":0},{"timestamp":"2026-02-01T00:44:39.119Z","count":0,"uniques":0},{"timestamp":"2026-02-02T00:40:00.846Z","count":0,"uniques":0},{"timestamp":"2026-02-03T00:39:49.261Z","count":0,"uniques":0},{"timestamp":"2026-02-04T00:35:57.727Z","count":0,"uniques":0},{"timestamp":"2026-02-05T00:39:50.175Z","count":0,"uniques":0},{"timestamp":"2026-02-06T00:36:58.566Z","count":0,"uniques":0},{"timestamp":"2026-02-07T00:37:19.162Z","count":0,"uniques":0},{"timestamp":"2026-02-08T00:49:17.066Z","count":0,"uniques":0},{"timestamp":"2026-02-09T00:40:31.156Z","count":0,"uniques":0},{"timestamp":"2026-02-10T00:45:28.144Z","count":0,"uniques":0}]
